xorjson-3.10.5.dist-info/METADATA
xorjson-3.10.5.dist-info/WHEEL
xorjson-3.10.5.dist-info/license_files/LICENSE-APACHE
xorjson-3.10.5.dist-info/license_files/LICENSE-MIT
xorjson/__init__.pyi
xorjson/__init__.py
xorjson/py.typed
xorjson/xorjson.cpython-311-darwin.so
xorjson-3.10.5.dist-info/RECORD
